trec_car/__init__.py
trec_car/format_runs.py
trec_car/read_data.py
trec_car_tools-2.6.dist-info/LICENSE.txt
trec_car_tools-2.6.dist-info/METADATA
trec_car_tools-2.6.dist-info/WHEEL
trec_car_tools-2.6.dist-info/top_level.txt
trec_car_tools-2.6.dist-info/RECORD
